popups/__init__.py
popups/dismiss.py
popups/settings.py
popups/tpl/app/a.png
popups/tpl/app/b.png
popups/tpl/app/c.png
popups/tpl/app/d.jpg
popups/tpl/app/d.png
popups/tpl/sys/android/a.png
popups/tpl/sys/android/b_0.png
popups/tpl/sys/android/b_1.png
popups/tpl/sys/android/b_2.png
popups/tpl/sys/android/c.png
popups/tpl/sys/android/d.png
popups-0.0.5.dist-info/LICENSE
popups-0.0.5.dist-info/METADATA
popups-0.0.5.dist-info/WHEEL
popups-0.0.5.dist-info/top_level.txt
popups-0.0.5.dist-info/RECORD
