Metadata-Version: 2.1
Name: popups
Version: 0.0.5
Summary: General pop-up processing!
Home-page: https://github.com/openutx/popups
Author: lijiawei
Author-email: jiawei.li2@qq.com
License: Apache License 2.0
Keywords: utx,popups,airtest,tools
Platform: any
Classifier: Development Status :: 5 - Production/Stable
Classifier: Environment :: Console :: Curses
Classifier: Operating System :: MacOS
Classifier: Operating System :: POSIX
Classifier: Operating System :: Microsoft :: Windows
Classifier: Programming Language :: Python :: 3 :: Only
Classifier: Programming Language :: Python :: 3.6
Classifier: Programming Language :: Python :: 3.7
Classifier: Programming Language :: Python :: 3.8
Classifier: Programming Language :: Python :: 3.9
Classifier: Programming Language :: Python :: Implementation :: CPython
License-File: LICENSE
